astroforge/__init__.py
astroforge/common.py
astroforge/constants.py
astroforge/coordinates/__init__.py
astroforge/coordinates/_base_rotations.py
astroforge/coordinates/_transformations.py
astroforge/coordinates/_utilities.py
astroforge/coordinates/nutation_data.json
astroforge/coordinates/iers/__init__.py
astroforge/coordinates/iers/_iers_utils.py
astroforge/force_models/__init__.py
astroforge/force_models/_forces.py
astroforge/force_models/_models.py
astroforge/propagators/__init__.py
astroforge/propagators/_propagator.py
astroforge/propagators/_wrapped.py
astroforge-0.3.1.dist-info/METADATA
astroforge-0.3.1.dist-info/WHEEL
astroforge-0.3.1.dist-info/licenses/LICENSE.txt
astroforge-0.3.1.dist-info/RECORD
