Metadata-Version: 2.4
Name: AstroForge
Version: 0.3.1
Summary: A Python library of astrodynamics tools
Project-URL: Documentation, https://astroforge.readthedocs.io/en/latest/
Project-URL: Repository, https://github.com/mit-ll/AstroForge
Author-email: Jake Varey <jakevarey@gmail.com>, Michael Tierney <michael.kotson@ll.mit.edu>
License-Expression: MIT
License-File: LICENSE.txt
Keywords: astrodynamics,space
Classifier: Development Status :: 4 - Beta
Classifier: Programming Language :: Python :: 3
Classifier: Programming Language :: Python :: 3.12
Classifier: Programming Language :: Python :: 3.13
Classifier: Programming Language :: Python :: 3.14
Requires-Python: >=3.12
Requires-Dist: numba
Requires-Dist: numpy
Requires-Dist: requests
Requires-Dist: scipy
